sonos/__init__.py
sonos/main.py
sonos/utils.py
sonos/webserver.py
sonos/etc/settings.yaml
sonos_artwork-1.3.2.dist-info/METADATA
sonos_artwork-1.3.2.dist-info/WHEEL
sonos_artwork-1.3.2.dist-info/entry_points.txt
sonos_artwork-1.3.2.dist-info/top_level.txt
sonos_artwork-1.3.2.dist-info/RECORD
